linkcheck_pkg/__init__.py
linkcheck_pkg/link_check.py
src/__init__.py
src/link_check.py
tests/__init__.py
tests/sample_test.py
linkcheck_pkg_MLJBrackett-1.1.dist-info/METADATA
linkcheck_pkg_MLJBrackett-1.1.dist-info/WHEEL
linkcheck_pkg_MLJBrackett-1.1.dist-info/entry_points.txt
linkcheck_pkg_MLJBrackett-1.1.dist-info/top_level.txt
linkcheck_pkg_MLJBrackett-1.1.dist-info/RECORD
