Metadata-Version: 2.1
Name: linkcheck-pkg-MLJBrackett
Version: 1.1
Summary: A simple link checking program
Home-page: https://github.com/MLJBrackett/link-check
Author: Michael Brackett
Author-email: mljbrackett@gmail.com
License: MIT
Platform: UNKNOWN
Classifier: Programming Language :: Python :: 3
Classifier: License :: OSI Approved :: MIT License
Classifier: Operating System :: OS Independent
Requires-Python: >=3.8
Requires-Dist: requests
Requires-Dist: argparse
Requires-Dist: colorama
Requires-Dist: black
Requires-Dist: flake8
Requires-Dist: coverage
